ddtrace_graphql/__init__.py
ddtrace_graphql/base.py
ddtrace_graphql/patch.py
ddtrace_graphql/utils.py
ddtrace_graphql-0.2.0.dist-info/LICENSE
ddtrace_graphql-0.2.0.dist-info/METADATA
ddtrace_graphql-0.2.0.dist-info/WHEEL
ddtrace_graphql-0.2.0.dist-info/top_level.txt
ddtrace_graphql-0.2.0.dist-info/RECORD
