Metadata-Version: 2.1
Name: ddtrace-graphql
Version: 0.2.0
Summary: Python library for tracing graphql calls with Datadog
Home-page: https://github.com/beezz/ddtrace-graphql
Author: Michal Kuffa
Author-email: michal@bynder.com
License: UNKNOWN
Keywords: tracing datadog graphql graphene
Platform: UNKNOWN
Classifier: Intended Audience :: Developers
Classifier: Topic :: Software Development :: Debuggers
Classifier: License :: OSI Approved :: MIT License
Classifier: Programming Language :: Python :: 3
Classifier: Programming Language :: Python :: 3.5
Classifier: Programming Language :: Python :: 3.6
Requires-Dist: ddtrace
Requires-Dist: graphql-core
Requires-Dist: wrapt
Provides-Extra: test
Requires-Dist: tox ; extra == 'test'
Requires-Dist: pytest ; extra == 'test'
Requires-Dist: pytest-cov ; extra == 'test'
